rlquantdata/__init__.py
rlquantdata/client.py
rlquantdata/version.py
rlquantdata/DateUtilities/Asserts.py
rlquantdata/DateUtilities/Calendar.py
rlquantdata/DateUtilities/Date.py
rlquantdata/DateUtilities/DateUtilities.py
rlquantdata/DateUtilities/Date_enum.py
rlquantdata/DateUtilities/DayCounter.py
rlquantdata/DateUtilities/Period.py
rlquantdata/DateUtilities/Schedule.py
rlquantdata/DateUtilities/Settings.py
rlquantdata/DateUtilities/__init__.py
rlquantdata/utilities/__init__.py
rlquantdata/utilities/trade_date_utils.py
rlquantdata/utilities/utils.py
rlquantdata-1.0.7.dist-info/METADATA
rlquantdata-1.0.7.dist-info/WHEEL
rlquantdata-1.0.7.dist-info/top_level.txt
rlquantdata-1.0.7.dist-info/RECORD
