Metadata-Version: 2.4
Name: rlquantdata
Version: 1.0.7
Summary: A package for rl quant data sdk
Author: Ziheng Zhang
Author-email: zzh_main@qq.com
License: MIT
Classifier: Programming Language :: Python :: 3
Classifier: License :: OSI Approved :: MIT License
Classifier: Operating System :: Microsoft :: Windows
Classifier: Intended Audience :: Science/Research
Classifier: Intended Audience :: Developers
Requires-Python: >=3.6
Requires-Dist: numpy>=1.17.3
Requires-Dist: pandas>=1.0.0
Requires-Dist: pyarrow>=4.0.1
Dynamic: author
Dynamic: author-email
Dynamic: classifier
Dynamic: description
Dynamic: description-content-type
Dynamic: license
Dynamic: requires-dist
Dynamic: requires-python
Dynamic: summary
